README.txt
bootstrap.py
buildout.cfg
setup.cfg
setup.py
docs/HISTORY.txt
docs/INSTALL.txt
docs/LICENSE.GPL
docs/LICENSE.txt
src/collective/__init__.py
src/collective.feedfiller.egg-info/PKG-INFO
src/collective.feedfiller.egg-info/SOURCES.txt
src/collective.feedfiller.egg-info/dependency_links.txt
src/collective.feedfiller.egg-info/entry_points.txt
src/collective.feedfiller.egg-info/namespace_packages.txt
src/collective.feedfiller.egg-info/not-zip-safe
src/collective.feedfiller.egg-info/requires.txt
src/collective.feedfiller.egg-info/top_level.txt
src/collective/feedfiller/README.txt
src/collective/feedfiller/__init__.py
src/collective/feedfiller/adapters.py
src/collective/feedfiller/configure.zcml
src/collective/feedfiller/events.py
src/collective/feedfiller/filler.py
src/collective/feedfiller/flay.py
src/collective/feedfiller/flayregistry.py
src/collective/feedfiller/flayregistry.txt
src/collective/feedfiller/handlers.py
src/collective/feedfiller/handlers.txt
src/collective/feedfiller/interfaces.py
src/collective/feedfiller/openanything.py
src/collective/feedfiller/utils.py
src/collective/feedfiller/version.txt
src/collective/feedfiller/Extensions/Install.py
src/collective/feedfiller/Extensions/__init__.py
src/collective/feedfiller/browser/__init__.py
src/collective/feedfiller/browser/configure.zcml
src/collective/feedfiller/browser/feed.py
src/collective/feedfiller/browser/feedfiller.css
src/collective/feedfiller/browser/knewsticker.png
src/collective/feedfiller/browser/raw.pt
src/collective/feedfiller/browser/raw.py
src/collective/feedfiller/doc/__init__.py
src/collective/feedfiller/doc/integration.txt
src/collective/feedfiller/profiles/types.xml
src/collective/feedfiller/profiles/default/actions.xml
src/collective/feedfiller/profiles/default/catalog.xml
src/collective/feedfiller/profiles/default/types/FeedFeederItem.xml
src/collective/feedfiller/tests/Xtesturllib2.py
src/collective/feedfiller/tests/__init__.py
src/collective/feedfiller/tests/base.py
src/collective/feedfiller/tests/pageInspector.py
src/collective/feedfiller/tests/test_setup.py
src/collective/feedfiller/tests/tests.py
src/collective/feedfiller/tests/samples/BBCItem1.html
src/collective/feedfiller/tests/samples/BBCNews.xml
src/collective/feedfiller/tests/samples/examplefeed.xml
src/collective/feedfiller/tests/samples/samplefeed1.xml
src/collective/feedfiller/tests/samples/samplefeed2.xml
