Metadata-Version: 1.0
Name: collective.feedfiller
Version: 0.1dev-r77073
Summary: Expands FeedItems with the body of items referred to
Home-page: http://topia.com
Author: Russ Ferriday
Author-email: russf@topia.com
License: GPL
Keywords: FeedItem feedfeeder RSS feed
Platform: UNKNOWN
Classifier: Framework :: Plone
Classifier: Programming Language :: Python
Classifier: Topic :: Software Development :: Libraries :: Python Modules
